tracking_url/__init__.py
tracking_url/version.py
tracking_url/tests/test_tracking_url.py
tracking_url-0.0.4.dist-info/LICENSE.txt
tracking_url-0.0.4.dist-info/METADATA
tracking_url-0.0.4.dist-info/WHEEL
tracking_url-0.0.4.dist-info/top_level.txt
tracking_url-0.0.4.dist-info/RECORD
