Metadata-Version: 2.1
Name: tracking-url
Version: 0.0.4
Summary: Detect package carrier from tracking number and generate tracking url
Home-page: https://github.com/sereema/tracking-url
Author: Kevin Michel
Author-email: kevin.michel@sereema.com
License: UNKNOWN
Download-URL: https://github.com/sereema/tracking-url/archive/v0.0.4.tar.gz
Keywords: tracking,number,package,carrier,url,ups,fedex,usps,dhl
Platform: UNKNOWN
Classifier: Development Status :: 3 - Alpha
Classifier: Intended Audience :: Developers
Classifier: License :: OSI Approved :: MIT License
Classifier: Operating System :: OS Independent
Classifier: Programming Language :: Python
Classifier: Programming Language :: Python :: 3
Classifier: Programming Language :: Python :: 3.2
Classifier: Programming Language :: Python :: 3.3
Classifier: Programming Language :: Python :: 3.4
Classifier: Programming Language :: Python :: 3.4
Classifier: Programming Language :: Python :: 3.5
Classifier: Programming Language :: Python :: 3.6
Classifier: Topic :: Software Development :: Libraries :: Python Modules
